MANIFEST.in
pyproject.toml
setup.py
house_price_pred_mlops.egg-info/PKG-INFO
house_price_pred_mlops.egg-info/SOURCES.txt
house_price_pred_mlops.egg-info/dependency_links.txt
house_price_pred_mlops.egg-info/requires.txt
house_price_pred_mlops.egg-info/top_level.txt
regression_model/VERSION
regression_model/__init__.py
regression_model/config.yml
regression_model/pipeline.py
regression_model/predict.py
regression_model/train_pipeline.py
regression_model/config/__init__.py
regression_model/config/core.py
regression_model/datasets/__init__.py
regression_model/datasets/test.csv
regression_model/datasets/train.csv
regression_model/processing/__init__.py
regression_model/processing/data_manager.py
regression_model/processing/features.py
regression_model/processing/validation.py
regression_model/trained_models/__init__.py
regression_model/trained_models/regression_model_output_v0.0.1.pkl
requirements/requirements.txt
requirements/test_requirements.txt