Metadata-Version: 2.1
Name: house-price-pred-mlops
Version: 0.0.1
Summary: End-to-End House Price Prediction Regression Model Deployment Package with Scalable and Complete Production Pipeline using OpenSource.
Home-page: https://github.com/sg13041995/price-prediction-ml-model-production-pipeline-deployment
Author: SubhankarGhosh
Author-email: subhankar.130495@gmail.com
License: BSD-3
Classifier: License :: OSI Approved :: MIT License
Classifier: Programming Language :: Python
Classifier: Programming Language :: Python :: 3
Classifier: Programming Language :: Python :: 3.6
Classifier: Programming Language :: Python :: 3.7
Classifier: Programming Language :: Python :: 3.8
Classifier: Programming Language :: Python :: 3.9
Classifier: Programming Language :: Python :: Implementation :: CPython
Classifier: Programming Language :: Python :: Implementation :: PyPy
Requires-Python: >=3.6.0
